zaqar/__init__.py
zaqar/bootstrap.py
zaqar/context.py
zaqar/i18n.py
zaqar/version.py
zaqar/api/__init__.py
zaqar/api/handler.py
zaqar/api/v1_1/__init__.py
zaqar/api/v1_1/request.py
zaqar/api/v1_1/response.py
zaqar/api/v2/__init__.py
zaqar/api/v2/endpoints.py
zaqar/api/v2/request.py
zaqar/api/v2/response.py
zaqar/bench/__init__.py
zaqar/bench/conductor.py
zaqar/bench/config.py
zaqar/bench/consumer.py
zaqar/bench/helpers.py
zaqar/bench/observer.py
zaqar/bench/producer.py
zaqar/cmd/__init__.py
zaqar/cmd/gc.py
zaqar/cmd/server.py
zaqar/cmd/status.py
zaqar/common/__init__.py
zaqar/common/access.py
zaqar/common/auth.py
zaqar/common/cache.py
zaqar/common/cli.py
zaqar/common/consts.py
zaqar/common/decorators.py
zaqar/common/errors.py
zaqar/common/pipeline.py
zaqar/common/urls.py
zaqar/common/utils.py
zaqar/common/api/__init__.py
zaqar/common/api/api.py
zaqar/common/api/errors.py
zaqar/common/api/request.py
zaqar/common/api/response.py
zaqar/common/api/utils.py
zaqar/common/api/schemas/__init__.py
zaqar/common/api/schemas/flavors.py
zaqar/common/api/schemas/pools.py
zaqar/common/api/schemas/v1_1/__init__.py
zaqar/common/api/schemas/v1_1/flavors.py
zaqar/common/policies/__init__.py
zaqar/common/policies/base.py
zaqar/common/policies/claims.py
zaqar/common/policies/flavors.py
zaqar/common/policies/health.py
zaqar/common/policies/messages.py
zaqar/common/policies/pools.py
zaqar/common/policies/queues.py
zaqar/common/policies/subscription.py
zaqar/common/policies/topics.py
zaqar/common/storage/__init__.py
zaqar/common/storage/select.py
zaqar/common/transport/__init__.py
zaqar/common/transport/wsgi/__init__.py
zaqar/common/transport/wsgi/helpers.py
zaqar/conf/__init__.py
zaqar/conf/default.py
zaqar/conf/drivers.py
zaqar/conf/drivers_management_store_mongodb.py
zaqar/conf/drivers_management_store_redis.py
zaqar/conf/drivers_management_store_sqlalchemy.py
zaqar/conf/drivers_message_store_mongodb.py
zaqar/conf/drivers_message_store_redis.py
zaqar/conf/drivers_message_store_swift.py
zaqar-21.0.0.dist-info/AUTHORS
zaqar-21.0.0.dist-info/AUTHORS.rst
zaqar-21.0.0.dist-info/LICENSE
zaqar-21.0.0.dist-info/METADATA
zaqar-21.0.0.dist-info/WHEEL
zaqar-21.0.0.dist-info/entry_points.txt
zaqar-21.0.0.dist-info/pbr.json
zaqar-21.0.0.dist-info/top_level.txt
zaqar-21.0.0.dist-info/RECORD
