Metadata-Version: 2.1
Name: zaqar
Version: 21.0.0
Summary: OpenStack Queuing and Notification Service
Home-page: https://docs.openstack.org/zaqar/latest/
Author: OpenStack
Author-email: openstack-discuss@lists.openstack.org
Project-URL: Source, https://opendev.org/openstack/zaqar
Project-URL: Tracker, https://bugs.launchpad.net/zaqar
Classifier: Environment :: OpenStack
Classifier: Intended Audience :: Information Technology
Classifier: Intended Audience :: System Administrators
Classifier: License :: OSI Approved :: Apache Software License
Classifier: Operating System :: POSIX :: Linux
Classifier: Programming Language :: Python
Classifier: Programming Language :: Python :: Implementation :: CPython
Classifier: Programming Language :: Python :: 3 :: Only
Classifier: Programming Language :: Python :: 3
Classifier: Programming Language :: Python :: 3.10
Classifier: Programming Language :: Python :: 3.11
Classifier: Programming Language :: Python :: 3.12
Requires-Python: >=3.10
License-File: LICENSE
License-File: AUTHORS
License-File: AUTHORS.rst
Requires-Dist: pbr !=2.1.0,>=2.0.0
Requires-Dist: alembic >=0.9.6
Requires-Dist: cryptography >=2.7
Requires-Dist: falcon >=3.0.0
Requires-Dist: jsonschema >=3.2.0
Requires-Dist: keystonemiddleware >=9.1.0
Requires-Dist: msgpack >=1.0.0
Requires-Dist: python-swiftclient >=3.10.1
Requires-Dist: WebOb >=1.7.1
Requires-Dist: stevedore >=3.2.2
Requires-Dist: oslo.cache >=1.26.0
Requires-Dist: oslo.concurrency >=5.0.1
Requires-Dist: oslo.config >=8.3.2
Requires-Dist: oslo.context >=2.19.2
Requires-Dist: oslo.db >=11.0.0
Requires-Dist: oslo.i18n >=3.15.3
Requires-Dist: oslo.log >=4.6.1
Requires-Dist: oslo.messaging >=12.5.0
Requires-Dist: oslo.middleware >=3.31.0
Requires-Dist: oslo.reports >=2.2.0
Requires-Dist: oslo.serialization >=4.2.0
Requires-Dist: oslo.upgradecheck >=1.3.0
Requires-Dist: oslo.utils >=4.12.1
Requires-Dist: oslo.policy >=4.5.0
Requires-Dist: osprofiler >=1.4.0
Requires-Dist: SQLAlchemy >=1.3.19
Requires-Dist: autobahn >=22.3.2
Requires-Dist: requests >=2.25.0
Requires-Dist: futurist >=1.2.0
Provides-Extra: mongodb
Requires-Dist: pymongo >=3.6.0 ; extra == 'mongodb'
Provides-Extra: mysql
Requires-Dist: PyMySQL >=0.8.0 ; extra == 'mysql'
Provides-Extra: redis
Requires-Dist: redis >=3.4.0 ; extra == 'redis'
Provides-Extra: test
Requires-Dist: hacking <6.2.0,>=6.1.0 ; extra == 'test'
Requires-Dist: redis >=3.4.0 ; extra == 'test'
Requires-Dist: pymongo >=3.6.0 ; extra == 'test'
Requires-Dist: python-swiftclient >=3.10.1 ; extra == 'test'
Requires-Dist: websocket-client >=0.44.0 ; extra == 'test'
Requires-Dist: PyMySQL >=0.8.0 ; extra == 'test'
Requires-Dist: coverage !=4.4,>=4.0 ; extra == 'test'
Requires-Dist: cryptography >=2.7 ; extra == 'test'
Requires-Dist: ddt >=1.0.1 ; extra == 'test'
Requires-Dist: doc8 >=0.8.1 ; extra == 'test'
Requires-Dist: Pygments >=2.2.0 ; extra == 'test'
Requires-Dist: fixtures >=3.0.0 ; extra == 'test'
Requires-Dist: testscenarios >=0.4 ; extra == 'test'
Requires-Dist: testtools >=2.2.0 ; extra == 'test'
Requires-Dist: testresources >=2.0.0 ; extra == 'test'
Requires-Dist: oslotest >=3.2.0 ; extra == 'test'
Requires-Dist: stestr >=2.0.0 ; extra == 'test'
Requires-Dist: osprofiler >=1.4.0 ; extra == 'test'
